extargsparse/__init__.py
extargsparse/__key__.py
extargsparse/__lib__.py
extargsparse-1.1.2.dist-info/METADATA
extargsparse-1.1.2.dist-info/RECORD
extargsparse-1.1.2.dist-info/WHEEL
extargsparse-1.1.2.dist-info/top_level.txt
extargsparse-1.1.2.dist-info/zip-safe
