Metadata-Version: 2.1
Name: extargsparse
Version: 1.1.2
Summary: extension class for argparse with json configuration
Home-page: http://github.com/jeppeter/extargsparse
Author: jeppeter Wang
Author-email: jeppeter@gmail.com
License: MIT
Platform: UNKNOWN
Classifier: Programming Language :: Python
Classifier: License :: OSI Approved :: MIT License
Classifier: Operating System :: OS Independent
